main.py
source_clazar/__init__.py
source_clazar/manifest.yaml
source_clazar/run.py
source_clazar/source.py
airbyte_source_clazar-0.2.6.dist-info/METADATA
airbyte_source_clazar-0.2.6.dist-info/WHEEL
airbyte_source_clazar-0.2.6.dist-info/entry_points.txt
airbyte_source_clazar-0.2.6.dist-info/RECORD
